smoothintegration/__init__.py
smoothintegration/_http.py
smoothintegration/_version.py
smoothintegration/companies.py
smoothintegration/connections.py
smoothintegration/exact.py
smoothintegration/exceptions.py
smoothintegration/quickbooks.py
smoothintegration/request.py
smoothintegration/zohobooks.py
smoothintegration/data/__init__.py
smoothintegration/data/accounts.py
smoothintegration/data/balance_sheet.py
smoothintegration/data/bill_credits.py
smoothintegration/data/bills.py
smoothintegration/data/cdc.py
smoothintegration/data/customers.py
smoothintegration/data/invoice_credits.py
smoothintegration/data/invoices.py
smoothintegration/data/profit_and_loss.py
smoothintegration/data/suppliers.py
smoothintegration/data/types.py
smoothintegration-0.4.0.dist-info/licenses/LICENSE
smoothintegration-0.4.0.dist-info/METADATA
smoothintegration-0.4.0.dist-info/WHEEL
smoothintegration-0.4.0.dist-info/top_level.txt
smoothintegration-0.4.0.dist-info/RECORD
